click_pendulum/__init__.py
click_pendulum/datetime.py
click_pendulum/duration.py
click_pendulum-0.2.1.dist-info/METADATA
click_pendulum-0.2.1.dist-info/WHEEL
click_pendulum-0.2.1.dist-info/RECORD
