Metadata-Version: 2.1
Name: click-pendulum
Version: 0.2.1
Summary: Pendulum type support for click.
License: MIT
Author: Dawson R
Author-email: 105720-ddaws@users.noreply.gitlab.com
Requires-Python: >=3.12,<4.0
Classifier: License :: OSI Approved :: MIT License
Classifier: Programming Language :: Python :: 3
Classifier: Programming Language :: Python :: 3.12
Requires-Dist: click (>=8.0.0,<9.0.0)
Requires-Dist: pendulum (>=3.0.0,<4.0.0)
Requires-Dist: wheel (>=0.44.0,<0.45.0)
